{"v":"5.11.0","fr":60,"ip":0,"op":30,"w":168,"h":120,"nm":"杜比_on","ddd":0,"assets":[],"layers":[{"ddd":0,"ind":1,"ty":4,"nm":"fill1","sr":1,"ks":{"o":{"a":0,"k":100,"ix":11},"r":{"a":0,"k":0,"ix":10},"p":{"a":0,"k":[84,60,0],"ix":2,"l":2},"a":{"a":0,"k":[84,60,0],"ix":1,"l":2},"s":{"a":1,"k":[{"i":{"x":[0.833,0.833,0.833],"y":[0.833,0.833,0.833]},"o":{"x":[0.167,0.167,0.167],"y":[0.167,0.167,0.167]},"t":0,"s":[100,100,100]},{"i":{"x":[0.833,0.833,0.833],"y":[0.833,0.833,0.833]},"o":{"x":[0.167,0.167,0.167],"y":[0.167,0.167,0.167]},"t":5,"s":[104,104,100]},{"t":19,"s":[100,100,100]}],"ix":6,"l":2}},"ao":0,"shapes":[{"ty":"gr","it":[{"ind":0,"ty":"sh","ix":1,"ks":{"a":1,"k":[{"i":{"x":0.667,"y":1},"o":{"x":0.333,"y":0},"t":5,"s":[{"i":[[0,0],[0,0],[0,0],[0,0]],"o":[[0,0],[0,0],[0,0],[0,0]],"v":[[33,39],[-39,-39],[-33,-39],[39,39]],"c":true}]},{"t":26,"s":[{"i":[[0,0],[0,0],[0,0],[0,0]],"o":[[0,0],[0,0],[0,0],[0,0]],"v":[[-38.98,-38.99],[-39,-39],[-33,-39],[-32.98,-38.99]],"c":true}]}],"ix":2},"nm":"Path 1","mn":"ADBE Vector Shape - Group","hd":false},{"ty":"fl","c":{"a":0,"k":[1,1,1,1],"ix":4},"o":{"a":0,"k":100,"ix":5},"r":1,"bm":0,"nm":"Fill 1","mn":"ADBE Vector Graphic - Fill","hd":false},{"ty":"tr","p":{"a":0,"k":[84,60],"ix":2},"a":{"a":0,"k":[0,0],"ix":1},"s":{"a":0,"k":[100,100],"ix":3},"r":{"a":0,"k":0,"ix":6},"o":{"a":0,"k":100,"ix":7},"sk":{"a":0,"k":0,"ix":4},"sa":{"a":0,"k":0,"ix":5},"nm":"Transform"}],"nm":"Group 1","np":2,"cix":2,"bm":0,"ix":1,"mn":"ADBE Vector Group","hd":false}],"ip":0,"op":26,"st":0,"ct":1,"bm":0},{"ddd":0,"ind":2,"ty":4,"nm":"mask1","td":1,"sr":1,"ks":{"o":{"a":0,"k":100,"ix":11},"r":{"a":0,"k":0,"ix":10},"p":{"a":0,"k":[84,60,0],"ix":2,"l":2},"a":{"a":0,"k":[84,60,0],"ix":1,"l":2},"s":{"a":1,"k":[{"i":{"x":[0.833,0.833,0.833],"y":[0.833,0.833,0.833]},"o":{"x":[0.167,0.167,0.167],"y":[0.167,0.167,0.167]},"t":0,"s":[100,100,100]},{"i":{"x":[0.833,0.833,0.833],"y":[0.833,0.833,0.833]},"o":{"x":[0.167,0.167,0.167],"y":[0.167,0.167,0.167]},"t":5,"s":[104,104,100]},{"t":19,"s":[100,100,100]}],"ix":6,"l":2}},"ao":0,"shapes":[{"ty":"gr","it":[{"ind":0,"ty":"sh","ix":1,"ks":{"a":1,"k":[{"i":{"x":0.667,"y":1},"o":{"x":0.333,"y":0},"t":5,"s":[{"i":[[0,0],[0,0],[0,0],[0,0]],"o":[[0,0],[0,0],[0,0],[0,0]],"v":[[-48,-42],[-30,-42],[48,42],[30,42]],"c":true}]},{"t":26,"s":[{"i":[[0,0],[0,0],[0,0],[0,0]],"o":[[0,0],[0,0],[0,0],[0,0]],"v":[[-48,-42],[-30,-42],[-29.979,-42],[-47.979,-42]],"c":true}]}],"ix":2},"nm":"Path 1","mn":"ADBE Vector Shape - Group","hd":false},{"ty":"mm","mm":4,"nm":"Merge Paths 1","mn":"ADBE Vector Filter - Merge","hd":false},{"ty":"fl","c":{"a":0,"k":[0.850980451995,0.850980451995,0.850980451995,1],"ix":4},"o":{"a":0,"k":100,"ix":5},"r":1,"bm":0,"nm":"Fill 1","mn":"ADBE Vector Graphic - Fill","hd":false},{"ty":"tr","p":{"a":0,"k":[83.998,60],"ix":2},"a":{"a":0,"k":[0,0],"ix":1},"s":{"a":0,"k":[100,100],"ix":3},"r":{"a":0,"k":0,"ix":6},"o":{"a":0,"k":100,"ix":7},"sk":{"a":0,"k":0,"ix":4},"sa":{"a":0,"k":0,"ix":5},"nm":"Transform"}],"nm":"Group 1","np":3,"cix":2,"bm":0,"ix":1,"mn":"ADBE Vector Group","hd":false}],"ip":0,"op":120,"st":0,"ct":1,"bm":0},{"ddd":0,"ind":3,"ty":4,"nm":"fill2","tt":2,"tp":2,"sr":1,"ks":{"o":{"a":0,"k":100,"ix":11},"r":{"a":0,"k":0,"ix":10},"p":{"a":0,"k":[84,60,0],"ix":2,"l":2},"a":{"a":0,"k":[84,60,0],"ix":1,"l":2},"s":{"a":1,"k":[{"i":{"x":[0.833,0.833,0.833],"y":[0.833,0.833,0.833]},"o":{"x":[0.167,0.167,0.167],"y":[0.167,0.167,0.167]},"t":0,"s":[100,100,100]},{"i":{"x":[0.833,0.833,0.833],"y":[0.833,0.833,0.833]},"o":{"x":[0.167,0.167,0.167],"y":[0.167,0.167,0.167]},"t":5,"s":[104,104,100]},{"t":19,"s":[100,100,100]}],"ix":6,"l":2}},"ao":0,"shapes":[{"ty":"gr","it":[{"ind":0,"ty":"sh","ix":1,"ks":{"a":0,"k":{"i":[[0,0],[0,0],[0,0],[0,0],[0,0],[0,0],[0,0],[0.004,-0.011],[1.134,0.498],[0,0],[0,0],[0,0],[0,0],[0,0],[-1.231,2.708],[-0.944,2.06],[0,0]],"o":[[0,0],[0,0],[0,0],[0,0],[0,0],[0,0],[-0.004,0.011],[-0.508,1.114],[0,0],[0,0],[0,0],[0,0],[0,0],[2.756,1.205],[0.012,-0.022],[0,0],[0,0]],"v":[[61.85,-9.406],[56.329,-21.562],[51.702,-21.562],[59.537,-4.315],[59.381,-3.98],[59.324,-3.858],[57.626,-0.105],[57.615,-0.075],[54.632,1.047],[54.024,0.781],[52.839,3.385],[52.311,4.541],[52.319,4.545],[53.787,5.188],[61.024,2.461],[72,-21.558],[67.372,-21.558]],"c":true},"ix":2},"nm":"Path 1","mn":"ADBE Vector Shape - Group","hd":false},{"ind":1,"ty":"sh","ix":2,"ks":{"a":0,"k":{"i":[[0,3.175],[3.203,0],[0.774,-2.278],[0,-0.631],[-0.194,-0.57],[-2.59,0]],"o":[[0,-3.137],[-2.568,0],[-0.194,0.566],[0,0.628],[0.769,2.266],[3.203,0.004]],"v":[[48.001,-12.117],[42.162,-17.836],[36.624,-13.923],[36.322,-12.117],[36.624,-10.315],[42.162,-6.398]],"c":true},"ix":2},"nm":"Path 2","mn":"ADBE Vector Shape - Group","hd":false},{"ind":2,"ty":"sh","ix":3,"ks":{"a":0,"k":{"i":[[0,-5.232],[5.342,0],[1.569,1.076],[0,0],[0,0],[0,0],[0,0],[0,0],[-2.059,0]],"o":[[0,5.232],[-2.059,0],[0,0],[0,0],[0,0],[0,0],[0,0],[1.573,-1.076],[5.342,0]],"v":[[51.845,-12.079],[42.158,-2.592],[36.621,-4.303],[36.621,-2.588],[32.373,-2.588],[32.373,-29.992],[36.621,-29.992],[36.621,-19.855],[42.158,-21.566]],"c":true},"ix":2},"nm":"Path 3","mn":"ADBE Vector Shape - Group","hd":false},{"ind":3,"ty":"sh","ix":4,"ks":{"a":0,"k":{"i":[[0,0],[0,0],[0,0],[0,0]],"o":[[0,0],[0,0],[0,0],[0,0]],"v":[[24.577,-2.588],[28.812,-2.588],[28.812,-29.996],[24.577,-29.996]],"c":true},"ix":2},"nm":"Path 4","mn":"ADBE Vector Shape - Group","hd":false},{"ind":4,"ty":"sh","ix":5,"ks":{"a":0,"k":{"i":[[0,3.175],[3.203,0],[0,-3.171],[-3.238,0]],"o":[[0,-3.137],[-3.203,0],[0,3.137],[3.203,0]],"v":[[17.988,-12.117],[12.148,-17.836],[6.308,-12.117],[12.148,-6.398]],"c":true},"ix":2},"nm":"Path 5","mn":"ADBE Vector Shape - Group","hd":false},{"ind":5,"ty":"sh","ix":6,"ks":{"a":0,"k":{"i":[[0,-5.228],[5.343,0],[0,5.232],[-5.343,0]],"o":[[0,5.232],[-5.343,0],[0,-5.232],[5.343,0]],"v":[[21.835,-12.083],[12.148,-2.596],[2.46,-12.083],[12.148,-21.57]],"c":true},"ix":2},"nm":"Path 6","mn":"ADBE Vector Shape - Group","hd":false},{"ind":6,"ty":"sh","ix":7,"ks":{"a":0,"k":{"i":[[0,5.255],[5.362,0],[0,0],[0,0],[0,0],[0,0],[0,0]],"o":[[0,-5.255],[0,0],[0,0],[0,0],[0,0],[0,0],[5.362,0]],"v":[[-3.927,-16.311],[-13.665,-25.847],[-16.538,-25.847],[-19.524,-25.847],[-19.524,-6.771],[-16.538,-6.771],[-13.665,-6.771]],"c":true},"ix":2},"nm":"Path 7","mn":"ADBE Vector Shape - Group","hd":false},{"ind":7,"ty":"sh","ix":8,"ks":{"a":0,"k":{"i":[[0,-7.548],[7.707,0],[0,0],[0,0],[0,0]],"o":[[0,7.548],[0,0],[0,0],[0,0],[7.707,0]],"v":[[0.309,-16.311],[-13.669,-2.622],[-23.764,-2.622],[-23.764,-30],[-13.669,-30]],"c":true},"ix":2},"nm":"Path 8","mn":"ADBE Vector Shape - Group","hd":false},{"ind":8,"ty":"sh","ix":9,"ks":{"a":0,"k":{"i":[[0,0],[0,0],[0,-7.54],[-7.699,0],[0,0]],"o":[[0,0],[-7.699,0],[0,7.54],[0,0],[0,0]],"v":[[-32.229,-30],[-36.352,-30],[-50.33,-16.311],[-36.352,-2.622],[-32.229,-2.622]],"c":true},"ix":2},"nm":"Path 9","mn":"ADBE Vector Shape - Group","hd":false},{"ind":9,"ty":"sh","ix":10,"ks":{"a":0,"k":{"i":[[0,0],[0,0],[0,7.54],[7.7,0],[0,0]],"o":[[0,0],[7.7,0],[0,-7.54],[0,0],[0,0]],"v":[[-72,-2.622],[-67.876,-2.622],[-53.898,-16.311],[-67.876,-30],[-72,-30]],"c":true},"ix":2},"nm":"Path 10","mn":"ADBE Vector Shape - Group","hd":false},{"ind":10,"ty":"sh","ix":11,"ks":{"a":0,"k":{"i":[[0,0],[0,0],[0,0],[0,0],[0,0],[0,0],[0,0],[0,0],[0,0],[0,0],[0,0],[0,0]],"o":[[0,0],[0,0],[0,0],[0,0],[0,0],[0,0],[0,0],[0,0],[0,0],[0,0],[0,0],[0,0]],"v":[[31.852,29.996],[35.3,29.996],[35.3,15.334],[35.354,15.334],[44.553,29.996],[48.933,29.996],[48.933,11.019],[45.486,11.019],[45.486,25.224],[45.43,25.224],[36.426,11.019],[31.857,11.019]],"c":true},"ix":2},"nm":"Path 11","mn":"ADBE Vector Shape - Group","hd":false},{"ind":11,"ty":"sh","ix":12,"ks":{"a":0,"k":{"i":[[-0.295,0.772],[-0.531,0.574],[-0.746,0.327],[-0.921,0],[-0.749,-0.327],[-0.537,-0.575],[-0.291,-0.768],[0,-0.897],[0.292,-0.776],[0.545,-0.57],[0.753,-0.319],[0.904,0],[0.746,0.319],[0.544,0.574],[0.295,0.775],[0,0.932]],"o":[[0.291,-0.768],[0.536,-0.575],[0.741,-0.327],[0.921,0],[0.753,0.327],[0.536,0.574],[0.292,0.768],[0,0.932],[-0.291,0.775],[-0.543,0.574],[-0.752,0.319],[-0.9,0],[-0.741,-0.319],[-0.543,-0.573],[-0.291,-0.776],[0.008,-0.897]],"v":[[11.453,17.954],[12.691,15.943],[14.61,14.593],[17.102,14.102],[19.607,14.593],[21.537,15.943],[22.775,17.954],[23.213,20.456],[22.775,23.019],[21.52,25.041],[19.579,26.38],[17.098,26.86],[14.628,26.38],[12.699,25.041],[11.445,23.019],[11.006,20.456]],"c":true},"ix":2},"nm":"Path 12","mn":"ADBE Vector Shape - Group","hd":false},{"ind":12,"ty":"sh","ix":13,"ks":{"a":0,"k":{"i":[[-0.497,-1.164],[-0.878,-0.844],[-1.208,-0.467],[-1.421,0],[-1.215,0.465],[-0.884,0.845],[-0.494,1.167],[0,1.41],[0.494,1.167],[0.885,0.817],[1.216,0.441],[1.44,0],[1.203,-0.442],[0.878,-0.814],[0.493,-1.167],[0,-1.445]],"o":[[0.493,1.164],[0.878,0.841],[1.207,0.468],[1.44,0],[1.216,-0.467],[0.885,-0.84],[0.494,-1.164],[0,-1.445],[-0.494,-1.163],[-0.884,-0.818],[-1.215,-0.442],[-1.425,0],[-1.208,0.441],[-0.878,0.817],[-0.493,1.164],[-0.003,1.41]],"v":[[7.947,24.323],[10.004,27.334],[13.13,29.3],[17.075,30],[21.058,29.3],[24.211,27.334],[26.281,24.323],[27.023,20.46],[26.281,16.543],[24.211,13.57],[21.058,11.684],[17.075,11.023],[13.13,11.684],[10.004,13.57],[7.947,16.543],[7.204,20.46]],"c":true},"ix":2},"nm":"Path 13","mn":"ADBE Vector Shape - Group","hd":false},{"ind":13,"ty":"sh","ix":14,"ks":{"a":0,"k":{"i":[[0,0],[0,0],[0,0],[0,0]],"o":[[0,0],[0,0],[0,0],[0,0]],"v":[[-0.852,29.996],[2.596,29.996],[2.596,11.018],[-0.852,11.018]],"c":true},"ix":2},"nm":"Path 14","mn":"ADBE Vector Shape - Group","hd":false},{"ind":14,"ty":"sh","ix":15,"ks":{"a":0,"k":{"i":[[0,0],[0.959,0.323],[0.932,0],[0.804,-0.214],[0.633,-0.434],[0.392,-0.659],[0,-0.917],[-0.275,-0.567],[-0.443,-0.391],[-0.556,-0.237],[-0.555,-0.172],[-0.516,-0.168],[-0.38,-0.228],[-0.225,-0.312],[0,-0.474],[0.198,-0.332],[0.322,-0.221],[0.4,-0.095],[0.381,0],[0.754,0.353],[0.45,0.608],[0,0],[-1.141,-0.433],[-1.196,0],[-0.811,0.24],[-0.606,0.475],[-0.365,0.722],[0,0.965],[0.338,0.593],[0.528,0.392],[0.632,0.235],[0.59,0.186],[0.435,0.152],[0.303,0.201],[0.174,0.289],[0,0.407],[-0.198,0.316],[-0.311,0.197],[-0.384,0.095],[-0.381,0],[-0.633,-0.296],[-0.346,-0.441]],"o":[[-0.71,-0.642],[-0.959,-0.323],[-0.831,0],[-0.804,0.213],[-0.633,0.432],[-0.388,0.661],[0,0.847],[0.276,0.566],[0.442,0.392],[0.555,0.235],[0.571,0.186],[0.521,0.171],[0.381,0.229],[0.225,0.316],[0,0.491],[-0.198,0.331],[-0.322,0.22],[-0.4,0.095],[-0.726,0],[-0.753,-0.358],[0,0],[0.726,0.849],[1.142,0.433],[0.901,0],[0.816,-0.235],[0.606,-0.475],[0.365,-0.719],[0,-0.882],[-0.338,-0.593],[-0.528,-0.391],[-0.633,-0.237],[-0.52,-0.151],[-0.435,-0.152],[-0.302,-0.205],[-0.175,-0.289],[0,-0.441],[0.198,-0.312],[0.31,-0.194],[0.381,-0.092],[0.64,0],[0.633,0.297],[0,0]],"v":[[-6.094,12.953],[-8.598,11.505],[-11.44,11.023],[-13.894,11.342],[-16.049,12.308],[-17.583,13.947],[-18.165,16.312],[-17.75,18.433],[-16.67,19.87],[-15.175,20.81],[-13.514,21.422],[-11.879,21.954],[-10.528,22.551],[-9.619,23.365],[-9.281,24.547],[-9.58,25.78],[-10.361,26.605],[-11.44,27.076],[-12.609,27.217],[-14.83,26.685],[-16.635,25.236],[-18.973,27.372],[-16.17,29.293],[-12.663,29.944],[-10.093,29.585],[-7.965,28.517],[-6.509,26.723],[-5.965,24.194],[-6.47,21.981],[-7.767,20.505],[-9.506,19.567],[-11.339,18.931],[-12.768,18.475],[-13.871,17.943],[-14.585,17.205],[-14.845,16.163],[-14.546,15.03],[-13.781,14.266],[-12.741,13.832],[-11.599,13.692],[-9.689,14.136],[-8.221,15.243]],"c":true},"ix":2},"nm":"Path 15","mn":"ADBE Vector Shape - Group","hd":false},{"ind":15,"ty":"sh","ix":16,"ks":{"a":0,"k":{"i":[[0,0],[0,0],[0,0],[0,0]],"o":[[0,0],[0,0],[0,0],[0,0]],"v":[[-26.808,29.996],[-23.36,29.996],[-23.36,11.018],[-26.808,11.018]],"c":true},"ix":2},"nm":"Path 16","mn":"ADBE Vector Shape - Group","hd":false},{"ind":16,"ty":"sh","ix":17,"ks":{"a":0,"k":{"i":[[0,0],[0,0],[0,0],[0,0],[0,0],[0,0],[0,0],[0,0]],"o":[[0,0],[0,0],[0,0],[0,0],[0,0],[0,0],[0,0],[0,0]],"v":[[-48.932,11.019],[-45.073,11.019],[-39.734,25.627],[-39.625,25.627],[-34.232,11.019],[-30.508,11.019],[-38.282,29.996],[-41.264,29.996]],"c":true},"ix":2},"nm":"Path 17","mn":"ADBE Vector Shape - Group","hd":false},{"ty":"mm","mm":1,"nm":"Merge Paths 1","mn":"ADBE Vector Filter - Merge","hd":false},{"ty":"fl","c":{"a":0,"k":[1,1,1,1],"ix":4},"o":{"a":0,"k":100,"ix":5},"r":1,"bm":0,"nm":"Fill 1","mn":"ADBE Vector Graphic - Fill","hd":false},{"ty":"tr","p":{"a":0,"k":[84,60],"ix":2},"a":{"a":0,"k":[0,0],"ix":1},"s":{"a":0,"k":[100,100],"ix":3},"r":{"a":0,"k":0,"ix":6},"o":{"a":0,"k":100,"ix":7},"sk":{"a":0,"k":0,"ix":4},"sa":{"a":0,"k":0,"ix":5},"nm":"Transform"}],"nm":"Group 1","np":19,"cix":2,"bm":0,"ix":1,"mn":"ADBE Vector Group","hd":false}],"ip":0,"op":120,"st":0,"ct":1,"bm":0},{"ddd":0,"ind":4,"ty":4,"nm":"stroke1","sr":1,"ks":{"o":{"a":0,"k":24,"ix":11},"r":{"a":0,"k":0,"ix":10},"p":{"a":0,"k":[84,60,0],"ix":2,"l":2},"a":{"a":0,"k":[84,60,0],"ix":1,"l":2},"s":{"a":1,"k":[{"i":{"x":[0.833,0.833,0.833],"y":[0.833,0.833,0.833]},"o":{"x":[0.167,0.167,0.167],"y":[0.167,0.167,0.167]},"t":0,"s":[100,100,100]},{"i":{"x":[0.833,0.833,0.833],"y":[0.833,0.833,0.833]},"o":{"x":[0.167,0.167,0.167],"y":[0.167,0.167,0.167]},"t":5,"s":[104,104,100]},{"t":19,"s":[100,100,100]}],"ix":6,"l":2}},"ao":0,"shapes":[{"ty":"gr","it":[{"ind":0,"ty":"sh","ix":1,"ks":{"a":1,"k":[{"i":{"x":0.667,"y":1},"o":{"x":0.333,"y":0},"t":5,"s":[{"i":[[0,0],[0,0],[0,0],[0,0],[0,0]],"o":[[0,0],[0,0],[0,0],[0,0],[0,0]],"v":[[-32.212,-40.8],[43.112,40.801],[33,40.799],[32.211,40.801],[-43.112,-40.8]],"c":true}]},{"t":26,"s":[{"i":[[0,0],[0,0],[0,0],[0,0],[0,0]],"o":[[0,0],[0,0],[0,0],[0,0],[0,0]],"v":[[-32.212,-40.8],[-32.2,-40.793],[-42.312,-40.795],[-43.101,-40.793],[-43.112,-40.8]],"c":true}]}],"ix":2},"nm":"Path 1","mn":"ADBE Vector Shape - Group","hd":false},{"ty":"gr","it":[{"ty":"tr","p":{"a":0,"k":[0,0],"ix":2},"a":{"a":0,"k":[0,0],"ix":1},"s":{"a":0,"k":[100,100],"ix":3},"r":{"a":0,"k":0,"ix":6},"o":{"a":0,"k":100,"ix":7},"sk":{"a":0,"k":0,"ix":4},"sa":{"a":0,"k":0,"ix":5},"nm":"Transform"}],"nm":"Group 1","np":0,"cix":2,"bm":0,"ix":2,"mn":"ADBE Vector Group","hd":false},{"ty":"mm","mm":4,"nm":"Merge Paths 1","mn":"ADBE Vector Filter - Merge","hd":false},{"ty":"fl","c":{"a":0,"k":[0,0,0,1],"ix":4},"o":{"a":0,"k":100,"ix":5},"r":1,"bm":0,"nm":"Fill 1","mn":"ADBE Vector Graphic - Fill","hd":false},{"ty":"tr","p":{"a":0,"k":[84,60.001],"ix":2},"a":{"a":0,"k":[0,0],"ix":1},"s":{"a":0,"k":[100,100],"ix":3},"r":{"a":0,"k":0,"ix":6},"o":{"a":0,"k":100,"ix":7},"sk":{"a":0,"k":0,"ix":4},"sa":{"a":0,"k":0,"ix":5},"nm":"Transform"}],"nm":"Group 1","np":4,"cix":2,"bm":0,"ix":1,"mn":"ADBE Vector Group","hd":false}],"ip":0,"op":26,"st":0,"ct":1,"bm":0},{"ddd":0,"ind":5,"ty":4,"nm":"mask 2","td":1,"sr":1,"ks":{"o":{"a":0,"k":100,"ix":11},"r":{"a":0,"k":0,"ix":10},"p":{"a":0,"k":[84,60,0],"ix":2,"l":2},"a":{"a":0,"k":[84,60,0],"ix":1,"l":2},"s":{"a":1,"k":[{"i":{"x":[0.833,0.833,0.833],"y":[0.833,0.833,0.833]},"o":{"x":[0.167,0.167,0.167],"y":[0.167,0.167,0.167]},"t":0,"s":[100,100,100]},{"i":{"x":[0.833,0.833,0.833],"y":[0.833,0.833,0.833]},"o":{"x":[0.167,0.167,0.167],"y":[0.167,0.167,0.167]},"t":5,"s":[104,104,100]},{"t":19,"s":[100,100,100]}],"ix":6,"l":2}},"ao":0,"shapes":[{"ty":"gr","it":[{"ind":0,"ty":"sh","ix":1,"ks":{"a":1,"k":[{"i":{"x":0.667,"y":1},"o":{"x":0.333,"y":0},"t":5,"s":[{"i":[[0,0],[0,0],[0,0],[0,0]],"o":[[0,0],[0,0],[0,0],[0,0]],"v":[[-48,-42],[-30,-42],[48,42],[30,42]],"c":true}]},{"t":26,"s":[{"i":[[0,0],[0,0],[0,0],[0,0]],"o":[[0,0],[0,0],[0,0],[0,0]],"v":[[-48,-42],[-30,-42],[-29.979,-42],[-47.979,-42]],"c":true}]}],"ix":2},"nm":"Path 1","mn":"ADBE Vector Shape - Group","hd":false},{"ty":"mm","mm":4,"nm":"Merge Paths 1","mn":"ADBE Vector Filter - Merge","hd":false},{"ty":"fl","c":{"a":0,"k":[0.850980451995,0.850980451995,0.850980451995,1],"ix":4},"o":{"a":0,"k":100,"ix":5},"r":1,"bm":0,"nm":"Fill 1","mn":"ADBE Vector Graphic - Fill","hd":false},{"ty":"tr","p":{"a":0,"k":[83.998,60],"ix":2},"a":{"a":0,"k":[0,0],"ix":1},"s":{"a":0,"k":[100,100],"ix":3},"r":{"a":0,"k":0,"ix":6},"o":{"a":0,"k":100,"ix":7},"sk":{"a":0,"k":0,"ix":4},"sa":{"a":0,"k":0,"ix":5},"nm":"Transform"}],"nm":"Group 1","np":3,"cix":2,"bm":0,"ix":1,"mn":"ADBE Vector Group","hd":false}],"ip":0,"op":120,"st":0,"ct":1,"bm":0},{"ddd":0,"ind":6,"ty":4,"nm":"stroke2","tt":2,"tp":5,"sr":1,"ks":{"o":{"a":0,"k":24,"ix":11},"r":{"a":0,"k":0,"ix":10},"p":{"a":0,"k":[84,60,0],"ix":2,"l":2},"a":{"a":0,"k":[84,60,0],"ix":1,"l":2},"s":{"a":1,"k":[{"i":{"x":[0.833,0.833,0.833],"y":[0.833,0.833,0.833]},"o":{"x":[0.167,0.167,0.167],"y":[0.167,0.167,0.167]},"t":0,"s":[100,100,100]},{"i":{"x":[0.833,0.833,0.833],"y":[0.833,0.833,0.833]},"o":{"x":[0.167,0.167,0.167],"y":[0.167,0.167,0.167]},"t":5,"s":[104,104,100]},{"t":19,"s":[100,100,100]}],"ix":6,"l":2}},"ao":0,"shapes":[{"ty":"gr","it":[{"ind":0,"ty":"sh","ix":1,"ks":{"a":0,"k":{"i":[[0,0],[-1.308,0],[-2.102,-2.193],[0,0],[0,0],[0,0],[0,0],[0,0],[0,0],[0,0],[0.035,-0.068],[0,0],[3.615,1.58],[0,0],[0,0],[0,0],[0,0],[0,0],[0,0],[0,0],[0,0],[0,0],[0,0],[-0.096,0.204],[0,0],[0,0],[0,0],[0,-0.32],[6.301,0],[1.173,0.399],[0,0],[0,0],[0,0],[4.774,0],[0.92,5.352],[6.467,0],[0,0],[0,0],[0,0],[0,0],[0,0],[0,0],[0,0],[0,0],[0,7.312],[7.707,0],[0,0],[-0.616,-8.024],[-4.329,0],[-1.724,-4.119],[0,0],[0,0],[0,0]],"o":[[1.173,-0.399],[3.283,0],[0,0],[0,0],[0,0],[0,0],[0,0],[0,0],[0,0],[-0.921,2.01],[0,0],[-1.671,3.568],[0,0],[0,0],[0,0],[0,0],[0,0],[0,0],[0,0],[0,0],[0,0],[0,0],[0.243,0.107],[0,0],[0,0],[0,0],[0.026,0.313],[-0.002,6.261],[-1.307,0],[0,0],[0,0],[0,0],[-1.723,4.123],[-5.653,0],[-2.426,5.518],[0,0],[0,0],[0,0],[0,0],[0,0],[0,0],[0,0],[0,0],[7.375,-0.367],[-0.001,-7.548],[0,0],[8.266,0],[1.957,-3.514],[4.772,0],[0,0],[0,0],[0,0],[0,0]],"v":[[37.917,-22.743],[41.655,-23.367],[50.02,-19.807],[48.402,-23.361],[56.986,-23.361],[57.464,-22.306],[61.346,-13.761],[65.711,-23.358],[74.301,-23.358],[73.135,-20.809],[62.125,3.281],[62.119,3.278],[52.563,6.838],[51.095,6.194],[51.057,6.179],[51.024,6.161],[51.016,6.158],[49.442,5.388],[50.696,2.64],[52.615,-1.579],[54.241,-0.87],[54.851,-0.603],[54.854,-0.6],[55.469,-0.82],[55.483,-0.847],[57.051,-4.321],[53.096,-13.028],[53.144,-12.079],[41.655,-0.791],[37.917,-1.415],[37.917,-0.788],[22.272,-0.788],[22.272,-7.805],[11.644,-0.797],[0.32,-10.192],[-14.173,-0.823],[-26.067,-0.823],[-26.067,-31.799],[-14.173,-31.799],[-14.173,-30],[-24.269,-30],[-24.269,-2.622],[-14.173,-2.622],[-13.455,-2.639],[-0.195,-16.312],[-14.173,-30],[-14.173,-31.799],[1.554,-17.487],[11.644,-23.37],[22.272,-16.365],[22.272,-31.796],[30.109,-31.796],[37.917,-31.793]],"c":true},"ix":2},"nm":"Path 1","mn":"ADBE Vector Shape - Group","hd":false},{"ind":1,"ty":"sh","ix":2,"ks":{"a":0,"k":{"i":[[0,-2.94],[3.203,0.003],[0.769,2.266],[0.039,0.461],[0,0],[-0.112,0.439],[0,0],[-2.566,0],[0,0]],"o":[[0,3.175],[-2.59,0],[-0.145,-0.428],[0,0],[0,-0.474],[0,0],[0.774,-2.278],[0,0],[2.928,0.295]],"v":[[47.497,-12.117],[41.658,-6.398],[36.121,-10.315],[35.84,-11.651],[35.819,-12.117],[35.992,-13.491],[36.121,-13.922],[41.658,-17.836],[42.253,-17.806]],"c":true},"ix":2},"nm":"Path 2","mn":"ADBE Vector Shape - Group","hd":false},{"ind":2,"ty":"sh","ix":3,"ks":{"a":0,"k":{"i":[[0,0],[0,0],[-1.766,-0.136],[0,0],[-0.259,5.007],[0,0],[5.112,0.255],[0,0],[1.573,-1.077],[0,0],[0,0],[0,0]],"o":[[0,0],[1.373,0.942],[0,0],[5.176,0],[0,0],[0,-5.068],[0,0],[-2.058,0],[0,0],[0,0],[0,0],[0,0]],"v":[[36.118,-2.587],[36.118,-4.304],[40.891,-2.622],[41.655,-2.593],[51.329,-11.593],[51.341,-12.079],[42.153,-21.554],[41.655,-21.565],[36.118,-19.854],[36.118,-29.991],[31.87,-29.991],[31.87,-2.587]],"c":true},"ix":2},"nm":"Path 3","mn":"ADBE Vector Shape - Group","hd":false},{"ind":3,"ty":"sh","ix":4,"ks":{"a":0,"k":{"i":[[0,0],[0,0],[0,0],[0,0],[0,0],[0,0],[0,0],[0,0],[0,0],[0,0],[0,0]],"o":[[0,0],[0,0],[0,0],[0,0],[0,0],[0,0],[0,0],[0,0],[0,0],[0,0],[0,0]],"v":[[50.23,31.796],[43.053,31.796],[42.525,30.952],[36.599,21.507],[36.599,31.796],[29.55,31.796],[29.553,9.22],[36.912,9.22],[43.182,19.108],[43.182,9.22],[50.23,9.22]],"c":true},"ix":2},"nm":"Path 4","mn":"ADBE Vector Shape - Group","hd":false},{"ind":4,"ty":"sh","ix":5,"ks":{"a":0,"k":{"i":[[0,0],[0,0],[0,0],[0,0]],"o":[[0,0],[0,0],[0,0],[0,0]],"v":[[3.892,31.796],[-3.154,31.796],[-3.154,9.22],[3.892,9.22]],"c":true},"ix":2},"nm":"Path 5","mn":"ADBE Vector Shape - Group","hd":false},{"ind":5,"ty":"sh","ix":6,"ks":{"a":0,"k":{"i":[[0,0],[0,0],[0,0],[0,0],[0,0],[0,0],[0,0],[0,0],[0,0],[0,0],[0,0],[0,0]],"o":[[0,0],[0,0],[0,0],[0,0],[0,0],[0,0],[0,0],[0,0],[0,0],[0,0],[0,0],[0,0]],"v":[[-22.062,31.796],[-29.111,31.796],[-29.111,11.127],[-29.346,11.701],[-37.118,30.68],[-37.578,31.796],[-42.98,31.796],[-52.104,9.22],[-44.316,9.22],[-40.177,20.555],[-35.99,9.22],[-22.062,9.22]],"c":true},"ix":2},"nm":"Path 6","mn":"ADBE Vector Shape - Group","hd":false},{"ind":6,"ty":"sh","ix":7,"ks":{"a":0,"k":{"i":[[0,-1.654],[0.595,-1.41],[1.07,-1.016],[1.418,-0.546],[0,0],[1.64,0],[1.435,0.555],[1.056,1.012],[0,0],[0.585,1.379],[-0.005,1.628],[-0.597,1.412],[0,0],[-0.937,0.873],[0,0],[-1.419,0.519],[-1.612,0],[-1.433,-0.519],[-1.076,-0.993],[-0.59,-1.388]],"o":[[0,1.625],[-0.588,1.387],[-1.069,1.018],[0,0],[-1.438,0.548],[-1.619,0],[-1.418,-0.55],[0,0],[-1.058,-1.018],[-0.602,-1.411],[0.001,-1.65],[0,0],[0.567,-1.176],[0,0],[1.063,-0.984],[1.423,-0.521],[1.626,0],[1.421,0.516],[1.081,0.999],[0.597,1.416]],"v":[[28.319,20.461],[27.436,25.026],[24.947,28.641],[21.203,30.982],[21.197,30.982],[16.571,31.799],[11.978,30.979],[8.257,28.635],[8.254,28.632],[5.787,25.028],[4.902,20.455],[5.784,15.844],[6.016,15.331],[8.274,12.252],[8.277,12.249],[12.007,9.993],[16.571,9.223],[21.168,9.99],[24.93,12.246],[27.436,15.841]],"c":true},"ix":2},"nm":"Path 7","mn":"ADBE Vector Shape - Group","hd":false},{"ind":7,"ty":"sh","ix":8,"ks":{"a":0,"k":{"i":[[0,4.225],[4.403,0.001],[0,0],[0,0],[0,0],[0,0],[0,0],[0,0],[0,0],[0,-5.254],[5.361,-0.001],[0,0]],"o":[[-0.001,-4.224],[0,0],[0,0],[0,0],[0,0],[0,0],[0,0],[0,0],[5.361,0],[0,5.254],[0,0],[4.402,-0.001]],"v":[[-6.23,-16.312],[-14.167,-24.047],[-18.228,-24.047],[-18.228,-8.572],[-17.041,-8.572],[-17.041,-6.77],[-20.026,-6.77],[-20.026,-25.848],[-14.167,-25.848],[-4.432,-16.312],[-14.167,-6.77],[-14.167,-8.572]],"c":true},"ix":2},"nm":"Path 8","mn":"ADBE Vector Shape - Group","hd":false},{"ind":8,"ty":"sh","ix":9,"ks":{"a":0,"k":{"i":[[0,0],[0,0],[0,0],[0,0]],"o":[[0,0],[0,0],[0,0],[0,0]],"v":[[-14.167,-6.77],[-17.041,-6.77],[-17.041,-8.572],[-14.167,-8.572]],"c":true},"ix":2},"nm":"Path 9","mn":"ADBE Vector Shape - Group","hd":false},{"ind":9,"ty":"sh","ix":10,"ks":{"a":0,"k":{"i":[[0,0]],"o":[[0,0]],"v":[[-14.167,-8.572]],"c":false},"ix":2},"nm":"Path 10","mn":"ADBE Vector Shape - Group","hd":false},{"ind":10,"ty":"sh","ix":11,"ks":{"a":0,"k":{"i":[[0,2.139],[2.245,0],[0.525,-1.548],[0,0],[0,-0.423],[-0.135,-0.396],[-1.809,0]],"o":[[0,-2.107],[-1.794,0],[0,0],[-0.132,0.388],[0,0.417],[0.524,1.544],[2.249,0.002]],"v":[[45.698,-12.117],[41.658,-16.037],[37.826,-13.345],[37.823,-13.339],[37.618,-12.117],[37.826,-10.895],[41.658,-8.197]],"c":true},"ix":2},"nm":"Path 11","mn":"ADBE Vector Shape - Group","hd":false},{"ind":11,"ty":"sh","ix":12,"ks":{"a":0,"k":{"i":[[0,2.138],[2.245,0],[0,-2.135],[-2.273,-0.001],[0,0],[0.297,2.869],[0,0],[-3.204,0.001],[0,0],[0,-2.941],[0,0],[3.002,0],[0,0]],"o":[[0,-2.108],[-2.252,0.001],[0,2.114],[0,0],[-3.037,-0.001],[0,0],[0,-3.171],[0,0],[2.929,0.295],[0,0],[-0.302,2.895],[0,0],[2.252,0]],"v":[[15.684,-12.117],[11.644,-16.037],[7.604,-12.117],[11.644,-8.197],[11.644,-6.398],[5.834,-11.537],[5.805,-12.117],[11.644,-17.836],[12.238,-17.806],[17.485,-12.117],[17.453,-11.528],[11.644,-6.398],[11.644,-8.197]],"c":true},"ix":2},"nm":"Path 12","mn":"ADBE Vector Shape - Group","hd":false},{"ind":12,"ty":"sh","ix":13,"ks":{"a":0,"k":{"i":[[5.342,0],[0,-5.232],[0,0],[-4.948,-0.247],[0,0],[-0.258,5.007],[0,0]],"o":[[-5.343,0],[0,0],[0.251,4.845],[0,0],[5.175,0],[0,0],[0,-5.228]],"v":[[11.644,-21.571],[1.958,-12.082],[1.97,-11.596],[11.146,-2.607],[11.644,-2.596],[21.32,-11.596],[21.332,-12.082]],"c":true},"ix":2},"nm":"Path 13","mn":"ADBE Vector Shape - Group","hd":false},{"ind":13,"ty":"sh","ix":14,"ks":{"a":0,"k":{"i":[[0,0],[7.699,0],[0,0],[-0.338,-8.277],[-8.446,0],[0,0],[0,-7.54],[0,0],[-7.131,-0.356],[0,0],[0,0],[0,0],[0,0],[0,0],[0,0],[0,0],[0,0],[0.336,8.277],[8.446,0],[0,0],[0,0],[0,0],[0,0],[0,0],[0,0],[0,0],[-0.375,7.216]],"o":[[-0.001,-7.54],[0,0],[8.445,0],[0.338,-8.278],[0,0],[-7.7,0],[0,0],[0.362,6.983],[0,0],[0,0],[0,0],[0,0],[0,0],[0,0],[0,0],[0,0],[-8.447,0],[-0.337,8.277],[0,0],[0,0],[0,0],[0,0],[0,0],[0,0],[0,0],[7.459,0],[0,0]],"v":[[-54.4,-16.312],[-68.381,-30],[-68.381,-31.799],[-52.619,-16.939],[-36.854,-31.799],[-36.854,-30],[-50.832,-16.312],[-50.814,-15.609],[-37.572,-2.639],[-36.854,-2.622],[-32.732,-2.622],[-32.732,-30],[-36.854,-30],[-36.854,-31.799],[-30.931,-31.799],[-30.931,-0.823],[-36.854,-0.823],[-52.619,-15.685],[-68.381,-0.823],[-74.302,-0.823],[-74.302,-31.799],[-68.381,-31.799],[-68.381,-30],[-72.503,-30],[-72.503,-2.622],[-68.381,-2.622],[-54.421,-15.609]],"c":true},"ix":2},"nm":"Path 14","mn":"ADBE Vector Shape - Group","hd":false},{"ind":14,"ty":"sh","ix":15,"ks":{"a":0,"k":{"i":[[0,0],[0,0],[0,0],[0,0]],"o":[[0,0],[0,0],[0,0],[0,0]],"v":[[28.311,-29.997],[24.075,-29.997],[24.075,-2.587],[28.311,-2.587]],"c":true},"ix":2},"nm":"Path 15","mn":"ADBE Vector Shape - Group","hd":false},{"ind":15,"ty":"sh","ix":16,"ks":{"a":0,"k":{"i":[[0,0],[0,0],[0,0],[0,0],[0,0],[1.134,0.498],[0,0],[0,0],[0,0],[0,0],[0,0],[-1.231,2.707],[-0.944,2.06],[0,0],[0,0],[0,0],[0,0]],"o":[[0,0],[0,0],[0,0],[0,0],[-0.508,1.114],[0,0],[0,0],[0,0],[0,0],[0,0],[2.757,1.205],[0.011,-0.023],[0,0],[0,0],[0,0],[0,0],[0,0]],"v":[[59.034,-4.315],[58.879,-3.978],[58.82,-3.858],[57.124,-0.105],[57.112,-0.076],[54.13,1.046],[53.521,0.779],[52.337,3.387],[51.807,4.541],[51.815,4.544],[53.283,5.189],[60.52,2.461],[71.497,-21.559],[66.868,-21.559],[61.349,-9.407],[55.826,-21.562],[51.197,-21.562]],"c":true},"ix":2},"nm":"Path 16","mn":"ADBE Vector Shape - Group","hd":false},{"ind":16,"ty":"sh","ix":17,"ks":{"a":0,"k":{"i":[[0,0.74],[0.207,0.548],[0.368,0.395],[0.535,0.233],[0,0],[0.703,0],[0.483,-0.212],[0,0],[0.363,-0.39],[0.21,-0.554],[0,0],[0.006,-0.712],[-0.204,-0.547],[0,0],[-0.277,-0.293],[-0.525,-0.227],[-0.684,0],[0,0],[0,0],[0.559,0.239],[0.445,0.382],[0,0],[0.295,0.775],[0.056,0.67],[0,0],[-0.295,0.772],[-0.531,0.574],[-0.519,0.291],[0,0],[-0.92,0],[-0.749,-0.327],[-0.536,-0.575],[-0.291,-0.767],[0,-0.897],[0.291,-0.776],[0,0],[0.407,-0.428],[0.753,-0.319],[0,0],[0.679,0],[0,0],[-0.51,0.216],[-0.368,0.389],[0,0],[-0.211,0.561]],"o":[[0,-0.697],[-0.213,-0.561],[-0.36,-0.386],[0,0],[-0.495,-0.215],[-0.703,0],[0,0],[-0.528,0.232],[-0.369,0.399],[0,0],[-0.208,0.546],[0.002,0.729],[0,0],[0.19,0.389],[0.369,0.39],[0.498,0.213],[0,0],[0,0],[-0.647,-0.06],[-0.556,-0.239],[0,0],[-0.544,-0.574],[-0.218,-0.582],[0,0],[0.008,-0.897],[0.291,-0.767],[0.403,-0.432],[0,0],[0.742,-0.327],[0.921,0],[0.753,0.327],[0.536,0.574],[0.292,0.768],[0,0.932],[0,0],[-0.266,0.545],[-0.544,0.574],[0,0],[-0.592,0.18],[0,0],[0.687,0],[0.532,-0.226],[0,0],[0.367,-0.386],[0.207,-0.552]],"v":[[20.91,20.455],[20.588,18.592],[19.718,17.171],[18.388,16.245],[18.382,16.242],[16.598,15.903],[14.831,16.239],[14.828,16.242],[13.504,17.171],[12.634,18.592],[12.631,18.598],[12.303,20.473],[12.625,22.38],[12.801,22.787],[13.504,23.804],[14.837,24.727],[16.595,25.061],[16.595,26.86],[15.933,26.83],[14.125,26.379],[12.622,25.447],[12.194,25.043],[10.94,23.019],[10.53,21.141],[10.504,20.455],[10.949,17.953],[12.188,15.944],[13.568,14.86],[14.107,14.593],[16.598,14.101],[19.103,14.593],[21.033,15.944],[22.272,17.953],[22.709,20.455],[22.272,23.019],[22.029,23.581],[21.019,25.043],[19.076,26.379],[18.499,26.59],[16.595,26.86],[16.595,25.061],[18.373,24.724],[19.709,23.804],[19.715,23.801],[20.585,22.386]],"c":true},"ix":2},"nm":"Path 17","mn":"ADBE Vector Shape - Group","hd":false},{"ind":17,"ty":"sh","ix":18,"ks":{"a":0,"k":{"i":[[0,0],[0,0],[0,0],[0,0],[0,0],[0,0],[0,0],[0,0]],"o":[[0,0],[0,0],[0,0],[0,0],[0,0],[0,0],[0,0],[0,0]],"v":[[-49.435,11.019],[-41.768,29.997],[-38.785,29.997],[-31.013,11.019],[-34.736,11.019],[-40.13,25.626],[-40.238,25.626],[-45.576,11.019]],"c":true},"ix":2},"nm":"Path 18","mn":"ADBE Vector Shape - Group","hd":false},{"ind":18,"ty":"sh","ix":19,"ks":{"a":0,"k":{"i":[[0,0],[-0.511,-0.243],[-0.424,0],[0,0],[0,0],[0.374,0.133],[0,0],[0.451,0.608],[0,0],[-1.141,-0.433],[-0.886,-0.081],[0,0],[-0.811,0.239],[-0.493,0.312],[0,0],[-0.364,0.723],[-0.067,0.677],[0,0],[0.19,0.499],[0,0],[0.36,0.331],[0,0],[0.454,0.205],[0,0],[0.591,0.186],[0,0],[0.303,0.201],[0.154,0.199],[0,0],[0.032,0.283],[0,0],[-0.198,0.316],[-0.311,0.197],[-0.384,0.095],[-0.38,0],[0,0],[-0.475,-0.223],[-0.345,-0.441],[0,0],[0.959,0.323],[0.705,0.06],[0,0],[0.803,-0.213],[0.633,-0.434],[0,0],[0.295,-0.493],[0,-0.917],[0,0],[-0.206,-0.425],[-0.442,-0.391],[-0.555,-0.237],[-0.555,-0.171],[-0.516,-0.167],[-0.381,-0.228],[-0.225,-0.311],[0,-0.476],[0,0],[0.148,-0.248],[0,0],[0.241,-0.166],[0,0],[0.3,-0.071],[0,0],[0.19,0],[0,0],[-0.269,0.064],[-0.13,0.089],[-0.06,0.101],[0,0.245],[0.005,0.018],[0.18,0.107],[0.422,0.139],[0,0],[0.594,0.252],[0.592,0.523],[0.373,0.767],[0,1.034],[-0.579,0.987],[0,0],[-0.853,0.584],[-0.98,0.26],[-0.987,0],[-1.132,-0.382],[-0.903,-0.817],[0,0],[0,0],[0,0],[0.439,0.206],[0.353,0],[0.257,-0.061],[0.134,-0.083],[0.054,-0.086],[0.001,-0.006],[0,-0.082],[-0.003,-0.017],[-0.092,-0.065],[0,0],[-0.159,-0.056],[0,0],[0,0],[-0.654,-0.244],[-0.669,-0.496],[-0.456,-0.801],[0,-1.102],[0.516,-1.019],[0,0],[0.822,-0.646],[1.017,-0.295],[1.059,0],[1.341,0.509],[0.942,1.1],[0,0],[0,0]],"o":[[0.256,0.346],[0.55,0.259],[0,0],[0,0],[-0.367,-0.045],[0,0],[-0.753,-0.358],[0,0],[0.726,0.848],[0.856,0.325],[0,0],[0.901,0],[0.612,-0.177],[0,0],[0.606,-0.476],[0.274,-0.539],[0,0],[0,-0.662],[0,0],[-0.253,-0.445],[0,0],[-0.395,-0.294],[0,0],[-0.633,-0.237],[0,0],[-0.435,-0.153],[-0.227,-0.155],[0,0],[-0.131,-0.217],[0,0],[0,-0.441],[0.198,-0.311],[0.31,-0.194],[0.38,-0.092],[0,0],[0.479,0.056],[0.632,0.297],[0,0],[-0.71,-0.642],[-0.718,-0.242],[0,0],[-0.831,0],[-0.804,0.213],[0,0],[-0.429,0.368],[-0.388,0.662],[0,0],[0.053,0.583],[0.276,0.566],[0.443,0.392],[0.555,0.235],[0.571,0.187],[0.52,0.171],[0.38,0.228],[0.225,0.316],[0,0],[-0.037,0.337],[0,0],[-0.172,0.227],[0,0],[-0.256,0.142],[0,0],[-0.194,0.023],[0,0],[0.234,0],[0.196,-0.046],[0.114,-0.078],[-0.006,0.01],[0,-0.084],[-0.068,-0.089],[-0.238,-0.143],[0,0],[-0.612,-0.189],[-0.728,-0.31],[-0.629,-0.557],[-0.428,-0.879],[0,-1.175],[0,0],[0.523,-0.876],[0.819,-0.561],[0.954,-0.253],[1.139,0],[1.179,0.397],[0,0],[0,0],[0,0],[-0.133,-0.171],[-0.416,-0.195],[-0.222,0],[-0.203,0.051],[-0.091,0.058],[-0.001,0.003],[-0.006,0.021],[0,0.067],[0.027,0.041],[0,0],[0.116,0.055],[0,0],[0,0],[0.626,0.197],[0.786,0.293],[0.736,0.546],[0.532,0.935],[0,1.184],[0,0],[-0.479,0.948],[-0.799,0.627],[-0.99,0.292],[-1.418,0],[-1.393,-0.53],[0,0],[0,0],[0,0]],"v":[[-15.693,24.164],[-14.568,25.055],[-13.112,25.418],[-13.112,27.217],[-13.66,27.185],[-14.771,26.918],[-15.333,26.684],[-17.138,25.236],[-19.476,27.372],[-16.672,29.294],[-14.059,29.903],[-13.168,29.945],[-10.596,29.587],[-8.94,28.852],[-8.469,28.518],[-7.013,26.722],[-6.503,24.897],[-6.468,24.194],[-6.752,22.453],[-6.975,21.982],[-7.892,20.819],[-8.27,20.505],[-9.544,19.758],[-10.01,19.568],[-11.844,18.932],[-13.271,18.475],[-14.375,17.942],[-14.946,17.414],[-15.09,17.206],[-15.333,16.456],[-15.348,16.163],[-15.049,15.029],[-14.284,14.265],[-13.244,13.831],[-12.102,13.691],[-11.624,13.72],[-10.191,14.136],[-8.724,15.243],[-6.597,12.955],[-9.102,11.505],[-11.24,11.051],[-11.943,11.022],[-14.398,11.341],[-16.552,12.308],[-17.003,12.653],[-18.087,13.945],[-18.667,16.313],[-18.644,16.922],[-18.254,18.434],[-17.173,19.869],[-15.679,20.81],[-14.018,21.422],[-12.383,21.955],[-11.032,22.55],[-10.121,23.364],[-9.784,24.548],[-9.805,24.9],[-10.083,25.778],[-10.244,26.016],[-10.865,26.605],[-11.111,26.757],[-11.943,27.076],[-12.535,27.182],[-13.112,27.217],[-13.112,25.418],[-12.359,25.324],[-11.882,25.119],[-11.627,24.856],[-11.586,24.548],[-11.601,24.399],[-11.958,24.094],[-12.937,23.666],[-14.574,23.133],[-16.382,22.468],[-18.365,21.22],[-19.871,19.222],[-20.469,16.313],[-19.64,13.034],[-19.631,13.026],[-17.568,10.822],[-14.858,9.601],[-11.943,9.223],[-8.527,9.8],[-5.39,11.619],[-4.036,12.844],[-8.841,18.012],[-10.142,16.354],[-10.956,15.768],[-12.102,15.492],[-12.819,15.58],[-13.32,15.782],[-13.531,15.996],[-13.534,16.011],[-13.549,16.163],[-13.54,16.286],[-13.376,16.445],[-13.089,16.609],[-12.676,16.776],[-11.337,17.203],[-11.302,17.215],[-9.383,17.88],[-7.197,19.061],[-5.41,21.091],[-4.669,24.194],[-5.407,27.53],[-5.404,27.533],[-7.358,29.933],[-10.089,31.31],[-13.168,31.743],[-17.311,30.976],[-20.844,28.544],[-21.978,27.22],[-16.88,22.559]],"c":true},"ix":2},"nm":"Path 19","mn":"ADBE Vector Shape - Group","hd":false},{"ind":19,"ty":"sh","ix":20,"ks":{"a":0,"k":{"i":[[0,0],[0,0],[0,0],[0,0],[0,0],[0,0],[0,0],[0,0],[0,0],[0,0],[0,0],[0,0]],"o":[[0,0],[0,0],[0,0],[0,0],[0,0],[0,0],[0,0],[0,0],[0,0],[0,0],[0,0],[0,0]],"v":[[44.98,11.019],[44.98,25.225],[44.928,25.225],[35.922,11.019],[31.355,11.019],[31.349,29.997],[34.797,29.997],[34.797,15.334],[34.853,15.334],[44.049,29.997],[48.429,29.997],[48.429,11.019]],"c":true},"ix":2},"nm":"Path 20","mn":"ADBE Vector Shape - Group","hd":false},{"ind":20,"ty":"sh","ix":21,"ks":{"a":0,"k":{"i":[[0,0],[0,0],[0,0],[0,0]],"o":[[0,0],[0,0],[0,0],[0,0]],"v":[[2.093,11.019],[-1.355,11.019],[-1.355,29.998],[2.093,29.998]],"c":true},"ix":2},"nm":"Path 21","mn":"ADBE Vector Shape - Group","hd":false},{"ind":21,"ty":"sh","ix":22,"ks":{"a":0,"k":{"i":[[0,0]],"o":[[0,0]],"v":[[2.093,29.997]],"c":false},"ix":2},"nm":"Path 22","mn":"ADBE Vector Shape - Group","hd":false},{"ind":22,"ty":"sh","ix":23,"ks":{"a":0,"k":{"i":[[0,0],[0,0],[0,0],[0,0]],"o":[[0,0],[0,0],[0,0],[0,0]],"v":[[-23.864,11.019],[-27.312,11.019],[-27.312,29.998],[-23.864,29.998]],"c":true},"ix":2},"nm":"Path 23","mn":"ADBE Vector Shape - Group","hd":false},{"ind":23,"ty":"sh","ix":24,"ks":{"a":0,"k":{"i":[[0,0]],"o":[[0,0]],"v":[[-23.864,29.997]],"c":false},"ix":2},"nm":"Path 24","mn":"ADBE Vector Shape - Group","hd":false},{"ind":24,"ty":"sh","ix":25,"ks":{"a":0,"k":{"i":[[0,0],[0.378,1.052],[0,0],[0.733,0.754],[0,0],[0.849,0.4],[0,0],[1.441,0],[1.203,-0.441],[0,0],[0.658,-0.61],[0.494,-1.167],[0,-1.444],[-0.497,-1.163],[-0.878,-0.845],[-1.207,-0.468],[-1.026,-0.087],[0,0],[-1.088,0.356],[0,0],[-0.885,0.844],[-0.493,1.167],[-0.055,1.208]],"o":[[0,-1.265],[0,0],[-0.431,-1.018],[0,0],[-0.664,-0.613],[0,0],[-1.216,-0.442],[-1.425,0],[0,0],[-0.843,0.401],[-0.878,0.818],[-0.493,1.163],[-0.004,1.41],[0.494,1.164],[0.877,0.84],[0.905,0.351],[0,0],[1.26,0],[0,0],[1.215,-0.468],[0.885,-0.841],[0.432,-1.018],[0,0]],"v":[[26.521,20.461],[25.952,16.986],[25.776,16.544],[24.03,13.884],[23.708,13.57],[21.438,12.05],[20.556,11.684],[16.571,11.022],[12.628,11.684],[11.752,12.05],[9.502,13.57],[7.442,16.544],[6.701,20.461],[7.442,24.322],[9.502,27.334],[12.628,29.3],[15.525,29.956],[16.571,30],[20.093,29.464],[20.556,29.3],[23.708,27.334],[25.776,24.322],[26.509,20.983]],"c":true},"ix":2},"nm":"Path 25","mn":"ADBE Vector Shape - Group","hd":false},{"ty":"mm","mm":1,"nm":"Merge Paths 1","mn":"ADBE Vector Filter - Merge","hd":false},{"ty":"mm","mm":4,"nm":"Merge Paths 2","mn":"ADBE Vector Filter - Merge","hd":false},{"ty":"fl","c":{"a":0,"k":[0,0,0,1],"ix":4},"o":{"a":0,"k":100,"ix":5},"r":1,"bm":0,"nm":"Fill 1","mn":"ADBE Vector Graphic - Fill","hd":false},{"ty":"tr","p":{"a":0,"k":[84.503,60],"ix":2},"a":{"a":0,"k":[0,0],"ix":1},"s":{"a":0,"k":[100,100],"ix":3},"r":{"a":0,"k":0,"ix":6},"o":{"a":0,"k":100,"ix":7},"sk":{"a":0,"k":0,"ix":4},"sa":{"a":0,"k":0,"ix":5},"nm":"Transform"}],"nm":"Group 1","np":28,"cix":2,"bm":0,"ix":1,"mn":"ADBE Vector Group","hd":false}],"ip":0,"op":120,"st":0,"ct":1,"bm":0},{"ddd":0,"ind":7,"ty":4,"nm":"mask 3","td":1,"sr":1,"ks":{"o":{"a":0,"k":100,"ix":11},"r":{"a":0,"k":0,"ix":10},"p":{"a":0,"k":[84,60,0],"ix":2,"l":2},"a":{"a":0,"k":[84,60,0],"ix":1,"l":2},"s":{"a":1,"k":[{"i":{"x":[0.833,0.833,0.833],"y":[0.833,0.833,0.833]},"o":{"x":[0.167,0.167,0.167],"y":[0.167,0.167,0.167]},"t":0,"s":[100,100,100]},{"i":{"x":[0.833,0.833,0.833],"y":[0.833,0.833,0.833]},"o":{"x":[0.167,0.167,0.167],"y":[0.167,0.167,0.167]},"t":5,"s":[104,104,100]},{"t":19,"s":[100,100,100]}],"ix":6,"l":2}},"ao":0,"shapes":[{"ty":"gr","it":[{"ind":0,"ty":"sh","ix":1,"ks":{"a":1,"k":[{"i":{"x":0.667,"y":1},"o":{"x":0.333,"y":0},"t":5,"s":[{"i":[[0,0],[0,0],[0,0],[0,0]],"o":[[0,0],[0,0],[0,0],[0,0]],"v":[[-48,-42],[-30,-42],[48,42],[30,42]],"c":true}]},{"t":26,"s":[{"i":[[0,0],[0,0],[0,0],[0,0]],"o":[[0,0],[0,0],[0,0],[0,0]],"v":[[-48,-42],[-30,-42],[-29.979,-42],[-47.979,-42]],"c":true}]}],"ix":2},"nm":"Path 1","mn":"ADBE Vector Shape - Group","hd":false},{"ty":"mm","mm":4,"nm":"Merge Paths 1","mn":"ADBE Vector Filter - Merge","hd":false},{"ty":"fl","c":{"a":0,"k":[0.850980451995,0.850980451995,0.850980451995,1],"ix":4},"o":{"a":0,"k":100,"ix":5},"r":1,"bm":0,"nm":"Fill 1","mn":"ADBE Vector Graphic - Fill","hd":false},{"ty":"tr","p":{"a":0,"k":[83.998,60],"ix":2},"a":{"a":0,"k":[0,0],"ix":1},"s":{"a":0,"k":[100,100],"ix":3},"r":{"a":0,"k":0,"ix":6},"o":{"a":0,"k":100,"ix":7},"sk":{"a":0,"k":0,"ix":4},"sa":{"a":0,"k":0,"ix":5},"nm":"Transform"}],"nm":"Group 1","np":3,"cix":2,"bm":0,"ix":1,"mn":"ADBE Vector Group","hd":false}],"ip":0,"op":120,"st":0,"ct":1,"bm":0},{"ddd":0,"ind":8,"ty":4,"nm":"stroke3","tt":1,"tp":7,"sr":1,"ks":{"o":{"a":0,"k":24,"ix":11},"r":{"a":0,"k":0,"ix":10},"p":{"a":0,"k":[84,60,0],"ix":2,"l":2},"a":{"a":0,"k":[84,60,0],"ix":1,"l":2},"s":{"a":1,"k":[{"i":{"x":[0.833,0.833,0.833],"y":[0.833,0.833,0.833]},"o":{"x":[0.167,0.167,0.167],"y":[0.167,0.167,0.167]},"t":0,"s":[100,100,100]},{"i":{"x":[0.833,0.833,0.833],"y":[0.833,0.833,0.833]},"o":{"x":[0.167,0.167,0.167],"y":[0.167,0.167,0.167]},"t":5,"s":[104,104,100]},{"t":19,"s":[100,100,100]}],"ix":6,"l":2}},"ao":0,"shapes":[{"ty":"gr","it":[{"ind":0,"ty":"sh","ix":1,"ks":{"a":0,"k":{"i":[[0,0],[0,0],[0,0],[0,0]],"o":[[0,0],[0,0],[0,0],[0,0]],"v":[[24.074,-3.131],[28.31,-3.131],[28.31,-30.54],[24.074,-30.54]],"c":true},"ix":2},"nm":"Path 1","mn":"ADBE Vector Shape - Group","hd":false},{"ind":1,"ty":"sh","ix":2,"ks":{"a":0,"k":{"i":[[0,0],[-1.309,0],[-2.101,-2.192],[0,0],[0,0],[0,0],[0,0],[0,0],[0,0],[0,0],[0,0],[0.649,-1.412],[0,0],[0.004,-0.01],[0.002,-0.003],[0,0],[3.617,1.581],[0,0],[0,0],[0,0],[0,0],[0,0],[-0.097,0.203],[0,0],[0,0],[0,0],[0,-0.323],[6.301,-0.001],[1.173,0.399],[0,0],[0,0],[0,0],[4.526,-0.226],[0,0],[0.912,5.36],[0.041,-0.09],[0,0],[0,0],[0,0],[0,0],[0,0.586],[4.016,0.402],[0,0],[0,0],[0,0],[0,0],[0,0],[0,0],[0,0],[0,0],[0,-5.254],[0.16,-0.683],[0,0],[0,2.001],[7.707,0],[0,0],[-0.611,-8.029],[-4.331,0],[0,0],[-1.651,-3.953],[0,0],[0,0],[0,0],[0,0]],"o":[[1.173,-0.399],[3.283,0],[0,0],[0,0],[0,0],[0,0],[0,0],[0,0],[0,0],[0,0],[-0.891,1.946],[0,0],[-0.004,0.01],[-0.012,0.025],[0,0],[-1.67,3.569],[0,0],[0,0],[0,0],[0,0],[0,0],[0.243,0.107],[0,0],[0,0],[0,0],[0.027,0.316],[0,6.261],[-1.308,0],[0,0],[0,0],[0,0],[-1.651,3.955],[0,0],[-5.658,0],[-0.039,0.09],[0,0],[0,0],[0,0],[0,0],[0.13,-0.553],[0,-3.961],[0,0],[0,0],[0,0],[0,0],[0,0],[0,0],[0,0],[0,0],[5.361,0.001],[0,0.729],[0,0],[0.792,-1.716],[-0.001,-7.548],[0,0],[8.269,0],[1.955,-3.518],[0,0],[4.525,0.226],[0,0],[0,0],[0,0],[0,0],[0,0]],"v":[[37.917,-23.286],[41.655,-23.908],[50.019,-20.352],[48.402,-23.904],[56.986,-23.904],[57.464,-22.85],[61.346,-14.301],[65.23,-22.848],[65.708,-23.902],[74.301,-23.902],[73.135,-21.352],[62.154,2.659],[62.157,2.661],[62.14,2.691],[62.122,2.734],[62.119,2.732],[52.562,6.294],[51.153,5.676],[49.334,5.07],[50.702,2.094],[52.615,-2.126],[54.851,-1.146],[55.469,-1.363],[55.483,-1.391],[57.054,-4.867],[53.096,-13.581],[53.14,-12.622],[41.655,-1.337],[37.917,-1.958],[37.917,-1.331],[22.275,-1.331],[22.275,-8.352],[12.229,-1.355],[11.643,-1.34],[0.317,-10.753],[0.203,-10.48],[-0.922,-8.044],[-5.996,-13.507],[-6.649,-14.208],[-6.43,-15.143],[-6.231,-16.855],[-13.353,-24.553],[-14.167,-24.594],[-16.291,-24.594],[-23.489,-32.342],[-14.173,-32.342],[-14.173,-30.544],[-19.361,-30.544],[-15.506,-26.393],[-14.167,-26.393],[-4.432,-16.855],[-4.678,-14.732],[-1.432,-11.236],[-0.195,-16.855],[-14.173,-30.544],[-14.173,-32.342],[1.554,-18.021],[11.643,-23.913],[12.232,-23.898],[22.275,-16.9],[22.275,-32.339],[30.109,-32.339],[30.109,-32.333],[37.917,-32.333]],"c":true},"ix":2},"nm":"Path 2","mn":"ADBE Vector Shape - Group","hd":false},{"ind":2,"ty":"sh","ix":3,"ks":{"a":0,"k":{"i":[[0,0],[0,0],[0.292,8.316],[8.475,0],[0,0],[0,0],[0,0],[0,0],[0,0],[0,0],[0,0],[0,7.54],[7.699,0],[0,0],[-0.329,-8.285],[-8.199,0.281],[0,0],[0,0],[0,0]],"o":[[0,0],[-8.475,0],[-0.293,8.317],[0,0],[0,0],[0,0],[0,0],[0,0],[0,0],[0,0],[7.7,0],[-0.001,-7.54],[0,0],[8.451,0],[0.321,-8.103],[0,0],[0,0],[0,0],[0,0]],"v":[[-30.934,-1.367],[-36.855,-1.367],[-52.616,-16.313],[-68.381,-1.367],[-74.302,-1.367],[-74.302,-32.342],[-68.381,-32.342],[-68.381,-30.544],[-72.503,-30.544],[-72.503,-3.165],[-68.381,-3.165],[-54.4,-16.855],[-68.381,-30.544],[-68.381,-32.342],[-52.619,-17.465],[-37.411,-32.331],[-36.591,-32.359],[-31.414,-26.785],[-30.934,-26.266]],"c":true},"ix":2},"nm":"Path 3","mn":"ADBE Vector Shape - Group","hd":false},{"ind":3,"ty":"sh","ix":4,"ks":{"a":0,"k":{"i":[[0,-3.137],[3.203,0.003],[0.769,2.266],[0,0.627],[-0.194,0.566],[-2.566,0]],"o":[[0,3.175],[-2.59,0],[-0.194,-0.571],[0,-0.631],[0.773,-2.278],[3.203,0]],"v":[[47.497,-12.66],[41.658,-6.941],[36.121,-10.859],[35.819,-12.66],[36.121,-14.465],[41.658,-18.38]],"c":true},"ix":2},"nm":"Path 4","mn":"ADBE Vector Shape - Group","hd":false},{"ind":4,"ty":"sh","ix":5,"ks":{"a":0,"k":{"i":[[0,0],[0,0],[0,0],[0,0],[0.803,0],[0,0],[0,0],[0,0],[0,0]],"o":[[0,0],[0,0],[0,0],[-0.766,0.113],[0,0],[0,0],[0,0],[0,0],[0,0]],"v":[[-18.228,-9.113],[-15.005,-9.113],[-8.434,-2.04],[-11.817,-1.54],[-14.173,-1.367],[-26.067,-1.367],[-26.067,-21.027],[-18.708,-13.102],[-18.228,-12.585]],"c":true},"ix":2},"nm":"Path 5","mn":"ADBE Vector Shape - Group","hd":false},{"ind":5,"ty":"sh","ix":6,"ks":{"a":0,"k":{"i":[[0,0],[0,0],[0,0],[0,0],[0,0],[0,0],[0,0],[0,0],[0,0],[0,0],[0,0],[0,0]],"o":[[0,0],[0,0],[0,0],[0,0],[0,0],[0,0],[0,0],[0,0],[0,0],[0,0],[0,0],[0,0]],"v":[[50.227,31.253],[43.053,31.253],[36.596,20.958],[36.596,32.359],[30.03,25.29],[29.547,24.773],[29.55,24.066],[29.556,8.676],[36.912,8.676],[43.182,18.564],[43.182,8.676],[50.227,8.676]],"c":true},"ix":2},"nm":"Path 6","mn":"ADBE Vector Shape - Group","hd":false},{"ind":6,"ty":"sh","ix":7,"ks":{"a":0,"k":{"i":[[0,0],[0,0],[0,0],[0,0],[0,0]],"o":[[0,0],[0,0],[0,0],[0,0],[0,0]],"v":[[-1.356,29.454],[2.093,29.454],[2.093,11.943],[0.727,10.475],[-1.356,10.475]],"c":true},"ix":2},"nm":"Path 7","mn":"ADBE Vector Shape - Group","hd":false},{"ind":7,"ty":"sh","ix":8,"ks":{"a":0,"k":{"i":[[0,0],[0,0],[0,0],[0,0],[0,0],[0,0],[0,0],[0,0],[0,0],[0,0],[0,0],[0,0],[0,0]],"o":[[0,0],[0,0],[0,0],[0,0],[0,0],[0,0],[0,0],[0,0],[0,0],[0,0],[0,0],[0,0],[0,0]],"v":[[-22.065,31.253],[-29.111,31.253],[-29.111,10.583],[-29.346,11.158],[-37.118,30.137],[-37.578,31.253],[-42.981,31.253],[-43.438,30.128],[-52.104,8.676],[-44.316,8.676],[-40.177,20.008],[-35.99,8.676],[-22.065,8.676]],"c":true},"ix":2},"nm":"Path 8","mn":"ADBE Vector Shape - Group","hd":false},{"ind":8,"ty":"sh","ix":9,"ks":{"a":0,"k":{"i":[[0,2.14],[2.046,0.207],[0,0],[0.526,-1.548],[0,0],[0,-0.424],[-0.076,-0.301],[0,0],[-1.809,0]],"o":[[0,-1.976],[0,0],[-1.793,0],[0,0],[-0.132,0.386],[0,0.314],[0,0],[0.525,1.544],[2.248,0.002]],"v":[[45.698,-12.66],[42.074,-16.557],[41.658,-16.581],[37.826,-13.889],[37.823,-13.882],[37.618,-12.66],[37.735,-11.738],[37.826,-11.438],[41.661,-8.74]],"c":true},"ix":2},"nm":"Path 9","mn":"ADBE Vector Shape - Group","hd":false},{"ind":9,"ty":"sh","ix":10,"ks":{"a":0,"k":{"i":[[0,2.137],[2.247,0],[0,-2.135],[-2.272,-0.001],[0,0],[0,3.137],[-3.203,0.001],[0,-3.137],[3.204,0],[0,0]],"o":[[0,-2.107],[-2.251,0],[0,2.114],[0,0],[-3.238,-0.001],[0,-3.171],[3.204,0],[0,3.175],[0,0],[2.254,0]],"v":[[15.686,-12.66],[11.643,-16.581],[7.603,-12.66],[11.643,-8.74],[11.643,-6.941],[5.805,-12.66],[11.643,-18.38],[17.485,-12.66],[11.643,-6.941],[11.643,-8.74]],"c":true},"ix":2},"nm":"Path 10","mn":"ADBE Vector Shape - Group","hd":false},{"ind":10,"ty":"sh","ix":11,"ks":{"a":0,"k":{"i":[[5.343,0],[0,-5.232],[-5.341,0],[-0.001,5.232]],"o":[[-5.342,0],[0,5.232],[5.343,0],[0,-5.228]],"v":[[11.643,-22.115],[1.958,-12.626],[11.643,-3.139],[21.332,-12.626]],"c":true},"ix":2},"nm":"Path 11","mn":"ADBE Vector Shape - Group","hd":false},{"ind":11,"ty":"sh","ix":12,"ks":{"a":0,"k":{"i":[[0,0],[0,0],[0,0],[0,0],[-0.683,0.1],[0,0],[0,0]],"o":[[0,0],[0,0],[0,0],[0.711,0],[0,0],[0,0],[0,0]],"v":[[-20.026,-11.878],[-24.269,-16.445],[-24.269,-3.165],[-14.173,-3.165],[-12.081,-3.32],[-15.79,-7.313],[-20.026,-7.313]],"c":true},"ix":2},"nm":"Path 12","mn":"ADBE Vector Shape - Group","hd":false},{"ind":12,"ty":"sh","ix":13,"ks":{"a":0,"k":{"i":[[0,0],[0,0],[0,-7.378],[-7.699,0],[0,0]],"o":[[0,0],[-7.471,0.256],[0,7.54],[0,0],[0,0]],"v":[[-32.732,-25.559],[-37.35,-30.531],[-50.832,-16.855],[-36.855,-3.165],[-32.732,-3.165]],"c":true},"ix":2},"nm":"Path 13","mn":"ADBE Vector Shape - Group","hd":false},{"ind":13,"ty":"sh","ix":14,"ks":{"a":0,"k":{"i":[[0,0],[0,0],[0,0],[0,0],[-2.058,0],[0,5.231],[5.342,0],[1.573,-1.077],[0,0]],"o":[[0,0],[0,0],[0,0],[1.569,1.076],[5.342,-0.001],[0,-5.232],[-2.058,0],[0,0],[0,0]],"v":[[31.87,-30.535],[31.87,-3.131],[36.118,-3.131],[36.118,-4.848],[41.655,-3.137],[51.341,-12.622],[41.655,-22.109],[36.118,-20.397],[36.118,-30.535]],"c":true},"ix":2},"nm":"Path 14","mn":"ADBE Vector Shape - Group","hd":false},{"ind":14,"ty":"sh","ix":15,"ks":{"a":0,"k":{"i":[[0,0],[0,0],[0,0],[0,0],[0,0],[0.004,-0.011],[1.134,0.498],[0,0],[0,0],[0,0],[0,0],[0,0],[-1.23,2.707],[-0.944,2.06],[0,0],[0,0],[0,0]],"o":[[0,0],[0,0],[0,0],[0,0],[-0.004,0.01],[-0.508,1.114],[0,0],[0,0],[0,0],[0,0],[0,0],[2.757,1.205],[0.012,-0.023],[0,0],[0,0],[0,0],[0,0]],"v":[[51.197,-22.105],[59.034,-4.859],[58.879,-4.521],[58.82,-4.402],[57.124,-0.648],[57.112,-0.62],[54.13,0.503],[53.52,0.236],[52.337,2.844],[51.807,3.997],[51.815,4.001],[53.283,4.645],[60.519,1.917],[71.497,-22.102],[66.868,-22.102],[61.349,-9.951],[55.826,-22.105]],"c":true},"ix":2},"nm":"Path 15","mn":"ADBE Vector Shape - Group","hd":false},{"ind":15,"ty":"sh","ix":16,"ks":{"a":0,"k":{"i":[[0,0],[0.364,0.86],[0.885,0.818],[1.215,0.441],[0.558,0.108]],"o":[[-0.096,-1.012],[-0.493,-1.163],[-0.885,-0.817],[-0.517,-0.188],[0,0]],"v":[[26.468,18.807],[25.776,16.001],[23.708,13.027],[20.556,11.141],[18.941,10.706]],"c":true},"ix":2},"nm":"Path 16","mn":"ADBE Vector Shape - Group","hd":false},{"ind":16,"ty":"sh","ix":17,"ks":{"a":0,"k":{"i":[[0,0],[-0.627,-0.227],[-1.075,-0.992],[-0.568,-1.174],[0,0],[-0.112,-1.181],[0,0],[0,0]],"o":[[0.625,0.121],[1.421,0.516],[0.947,0.875],[0,0],[0.439,1.041],[0,0],[0,0],[0,0]],"v":[[19.284,8.941],[21.171,9.447],[24.93,11.706],[27.203,14.788],[27.435,15.298],[28.261,18.637],[28.762,23.919],[13.87,7.895]],"c":true},"ix":2},"nm":"Path 17","mn":"ADBE Vector Shape - Group","hd":false},{"ind":17,"ty":"sh","ix":18,"ks":{"a":0,"k":{"i":[[0,0],[0,0],[0,0],[0,0],[0,0],[0,0],[0,0],[0,0]],"o":[[0,0],[0,0],[0,0],[0,0],[0,0],[0,0],[0,0],[0,0]],"v":[[-49.435,10.475],[-41.768,29.454],[-38.785,29.454],[-31.013,10.475],[-34.736,10.475],[-40.13,25.083],[-40.238,25.083],[-45.576,10.475]],"c":true},"ix":2},"nm":"Path 18","mn":"ADBE Vector Shape - Group","hd":false},{"ind":18,"ty":"sh","ix":19,"ks":{"a":0,"k":{"i":[[0,0],[0,-0.948],[-0.497,-1.163],[-0.878,-0.845],[-1.207,-0.468],[-1.421,0],[-0.541,0.075],[0,0],[0.381,0.163],[0.543,0.574],[0.295,0.775],[0.072,0.483]],"o":[[-0.212,0.828],[-0.004,1.41],[0.493,1.163],[0.877,0.84],[1.207,0.467],[0.577,0],[0,0],[-0.421,-0.08],[-0.741,-0.319],[-0.544,-0.574],[-0.163,-0.434],[0,0]],"v":[[7.02,17.251],[6.701,19.917],[7.442,23.779],[9.502,26.79],[12.628,28.757],[16.571,29.456],[18.247,29.339],[15.329,26.199],[14.125,25.835],[12.194,24.499],[10.94,22.475],[10.592,21.098]],"c":true},"ix":2},"nm":"Path 19","mn":"ADBE Vector Shape - Group","hd":false},{"ind":19,"ty":"sh","ix":20,"ks":{"a":0,"k":{"i":[[0,0],[-0.511,-0.243],[0,0],[-0.317,0],[0,0],[0.753,0.353],[0.45,0.608],[0,0],[-1.142,-0.434],[-1.195,0],[-0.811,0.239],[-0.605,0.474],[-0.365,0.722],[0,0.966],[0.338,0.592],[0.528,0.392],[0.633,0.236],[0.591,0.186],[0.435,0.151],[0.303,0.201],[0.174,0.288],[0,0.406],[-0.198,0.316],[-0.311,0.197],[-0.384,0.095],[-0.38,0],[-0.633,-0.297],[-0.345,-0.441],[0,0],[0.959,0.323],[0.931,0],[0.804,-0.213],[0.633,-0.434],[0.392,-0.658],[0,-0.917],[-0.275,-0.567],[-0.442,-0.391],[-0.555,-0.237],[-0.555,-0.171],[-0.516,-0.167],[-0.381,-0.228],[-0.225,-0.311],[0,-0.476],[0.198,-0.331],[0.322,-0.221],[0.399,-0.094],[0.38,0],[0,0],[-0.269,0.064],[-0.132,0.09],[-0.06,0.099],[-0.008,0.031],[0,0],[0.005,0.018],[0.05,0.045],[0,0],[0.429,0.142],[0.564,0.184],[0.593,0.252],[0.59,0.521],[0.376,0.772],[0,1.029],[-0.581,0.991],[0,0],[-0.851,0.582],[-0.982,0.259],[-0.986,0],[-1.131,-0.381],[-0.903,-0.816],[0,0],[0,0],[0,0],[0.437,0.205],[0.274,0.031],[0,0],[0.255,-0.061],[0.136,-0.084],[0.054,-0.086],[0.001,-0.006],[0,0],[-0.004,-0.02],[-0.094,-0.067],[-0.318,-0.111],[-0.488,-0.142],[0,0],[0,0],[-0.327,-0.122],[-0.671,-0.498],[-0.454,-0.798],[-0.085,-0.809],[0,0],[0.517,-1.019],[0,0],[0.822,-0.646],[1.021,-0.296],[0,0],[0.78,-0.053],[0,0],[1.34,0.508],[0.941,1.099],[0,0],[0,0]],"o":[[0.255,0.345],[0,0],[0.388,0.138],[0,0],[-0.726,0],[-0.753,-0.358],[0,0],[0.726,0.848],[1.141,0.433],[0.901,0],[0.815,-0.236],[0.606,-0.476],[0.365,-0.719],[0,-0.881],[-0.338,-0.593],[-0.527,-0.392],[-0.633,-0.236],[-0.519,-0.153],[-0.435,-0.153],[-0.302,-0.206],[-0.175,-0.289],[0,-0.441],[0.198,-0.311],[0.31,-0.194],[0.38,-0.092],[0.641,0],[0.632,0.297],[0,0],[-0.71,-0.642],[-0.959,-0.323],[-0.831,0],[-0.803,0.213],[-0.633,0.433],[-0.388,0.662],[0,0.847],[0.276,0.566],[0.442,0.392],[0.555,0.235],[0.571,0.187],[0.52,0.171],[0.38,0.228],[0.225,0.316],[0,0.489],[-0.198,0.331],[-0.322,0.219],[-0.4,0.095],[0,0],[0.234,0],[0.193,-0.046],[0.116,-0.079],[0.003,-0.007],[0,0],[0,-0.086],[-0.03,-0.039],[0,0],[-0.237,-0.142],[-0.517,-0.167],[-0.612,-0.19],[-0.732,-0.311],[-0.625,-0.554],[-0.429,-0.882],[0,-1.17],[0,0],[0.524,-0.879],[0.817,-0.56],[0.954,-0.253],[1.14,0],[1.18,0.397],[0,0],[0,0],[0,0],[-0.134,-0.172],[-0.312,-0.146],[0,0],[-0.222,0],[-0.204,0.051],[-0.087,0.056],[-0.001,0.003],[0,0],[0,0.063],[0.024,0.037],[0.157,0.104],[0.405,0.142],[0,0],[0,0],[0.32,0.112],[0.782,0.291],[0.739,0.548],[0.398,0.699],[0,0],[0,1.189],[0,0],[-0.478,0.946],[-0.8,0.627],[0,0],[-0.739,0.217],[0,0],[-1.418,0],[-1.394,-0.53],[0,0],[0,0],[0,0]],"v":[[-15.69,23.62],[-14.568,24.512],[-14.167,24.678],[-13.112,24.874],[-13.112,26.673],[-15.333,26.141],[-17.138,24.693],[-19.476,26.829],[-16.672,28.751],[-13.168,29.4],[-10.596,29.044],[-8.469,27.975],[-7.013,26.178],[-6.468,23.65],[-6.975,21.438],[-8.27,19.962],[-10.01,19.023],[-11.844,18.389],[-13.271,17.932],[-14.375,17.398],[-15.09,16.663],[-15.348,15.619],[-15.049,14.486],[-14.284,13.721],[-13.244,13.288],[-12.102,13.148],[-10.191,13.592],[-8.724,14.699],[-6.597,12.411],[-9.102,10.962],[-11.943,10.479],[-14.399,10.798],[-16.552,11.764],[-18.087,13.402],[-18.667,15.77],[-18.254,17.891],[-17.173,19.326],[-15.679,20.266],[-14.018,20.878],[-12.383,21.411],[-11.032,22.007],[-10.121,22.82],[-9.784,24.005],[-10.083,25.234],[-10.865,26.061],[-11.943,26.533],[-13.112,26.673],[-13.112,24.874],[-12.359,24.781],[-11.882,24.576],[-11.627,24.309],[-11.609,24.253],[-11.583,24.005],[-11.601,23.852],[-11.718,23.723],[-11.958,23.551],[-12.945,23.122],[-14.577,22.589],[-16.382,21.924],[-18.365,20.673],[-19.871,18.678],[-20.466,15.77],[-19.64,12.49],[-19.634,12.479],[-17.568,10.279],[-14.858,9.057],[-11.943,8.68],[-8.527,9.257],[-5.39,11.076],[-4.036,12.301],[-8.841,17.469],[-10.142,15.811],[-10.956,15.221],[-11.832,14.964],[-12.102,14.945],[-12.819,15.033],[-13.323,15.242],[-13.528,15.452],[-13.531,15.467],[-13.549,15.619],[-13.54,15.742],[-13.379,15.898],[-12.676,16.232],[-11.34,16.66],[-11.302,16.671],[-10.353,16.988],[-9.383,17.337],[-7.197,18.518],[-5.41,20.548],[-4.71,22.829],[-4.669,23.65],[-5.407,26.992],[-5.41,26.99],[-7.358,29.389],[-10.095,30.773],[-10.098,30.77],[-12.38,31.173],[-13.168,31.199],[-17.311,30.432],[-20.844,28.001],[-21.978,26.676],[-16.88,22.018]],"c":true},"ix":2},"nm":"Path 20","mn":"ADBE Vector Shape - Group","hd":false},{"ind":20,"ty":"sh","ix":21,"ks":{"a":0,"k":{"i":[[0,0],[0,0],[0,0],[0,0],[0,0]],"o":[[0,0],[0,0],[0,0],[0,0],[0,0]],"v":[[-3.154,8.676],[1.513,8.676],[3.892,11.234],[3.892,31.253],[-3.154,31.253]],"c":true},"ix":2},"nm":"Path 21","mn":"ADBE Vector Shape - Group","hd":false},{"ind":21,"ty":"sh","ix":22,"ks":{"a":0,"k":{"i":[[0,0],[0,0],[0,0],[0,0]],"o":[[0,0],[0,0],[0,0],[0,0]],"v":[[-23.864,10.475],[-27.312,10.475],[-27.312,29.454],[-23.864,29.454]],"c":true},"ix":2},"nm":"Path 22","mn":"ADBE Vector Shape - Group","hd":false},{"ind":22,"ty":"sh","ix":23,"ks":{"a":0,"k":{"i":[[0,0],[0,0],[0,0],[-0.111,-0.298],[0,0],[-0.276,-0.292],[-0.526,-0.228],[-0.301,-0.058],[0,0],[0,0],[0,0],[0,0],[0.321,-0.024],[0,0],[1.435,0.555],[1.056,1.012],[0,0],[0.586,1.381],[-0.004,1.625],[-0.254,0.987],[0,0]],"o":[[0,0],[0,0],[0.056,0.373],[0,0],[0.191,0.39],[0.364,0.385],[0.253,0.108],[0,0],[0,0],[0,0],[0,0],[-0.309,0.043],[0,0],[-1.62,0],[-1.417,-0.549],[0,0],[-1.058,-1.018],[-0.6,-1.409],[0,-1.081],[0,0],[0,0]],"v":[[11.91,19.874],[12.291,20.281],[12.373,20.831],[12.622,21.837],[12.801,22.243],[13.501,23.264],[14.831,24.18],[15.663,24.43],[16.246,24.54],[16.647,24.975],[21.918,30.646],[18.496,31.124],[17.55,31.221],[16.571,31.255],[11.977,30.436],[8.257,28.092],[8.254,28.089],[5.784,24.482],[4.902,19.911],[5.277,16.803],[6.098,13.613]],"c":true},"ix":2},"nm":"Path 23","mn":"ADBE Vector Shape - Group","hd":false},{"ind":23,"ty":"sh","ix":24,"ks":{"a":0,"k":{"i":[[0,0],[0,0],[0,0],[0,0],[0,0],[0,0],[0,0],[0,0],[0,0],[0,0],[0,0],[0,0]],"o":[[0,0],[0,0],[0,0],[0,0],[0,0],[0,0],[0,0],[0,0],[0,0],[0,0],[0,0],[0,0]],"v":[[44.98,10.475],[44.98,24.682],[44.928,24.682],[35.922,10.475],[31.354,10.475],[31.349,24.066],[34.797,27.777],[34.797,14.79],[34.852,14.79],[44.049,29.454],[48.429,29.454],[48.429,10.475]],"c":true},"ix":2},"nm":"Path 24","mn":"ADBE Vector Shape - Group","hd":false},{"ty":"mm","mm":1,"nm":"Merge Paths 1","mn":"ADBE Vector Filter - Merge","hd":false},{"ty":"gr","it":[{"ty":"tr","p":{"a":0,"k":[0,0],"ix":2},"a":{"a":0,"k":[0,0],"ix":1},"s":{"a":0,"k":[100,100],"ix":3},"r":{"a":0,"k":0,"ix":6},"o":{"a":0,"k":100,"ix":7},"sk":{"a":0,"k":0,"ix":4},"sa":{"a":0,"k":0,"ix":5},"nm":"Transform"}],"nm":"Group 1","np":0,"cix":2,"bm":0,"ix":26,"mn":"ADBE Vector Group","hd":false},{"ty":"mm","mm":4,"nm":"Merge Paths 2","mn":"ADBE Vector Filter - Merge","hd":false},{"ty":"fl","c":{"a":0,"k":[0,0,0,1],"ix":4},"o":{"a":0,"k":100,"ix":5},"r":1,"bm":0,"nm":"Fill 1","mn":"ADBE Vector Graphic - Fill","hd":false},{"ty":"tr","p":{"a":0,"k":[84.503,60.543],"ix":2},"a":{"a":0,"k":[0,0],"ix":1},"s":{"a":0,"k":[100,100],"ix":3},"r":{"a":0,"k":0,"ix":6},"o":{"a":0,"k":100,"ix":7},"sk":{"a":0,"k":0,"ix":4},"sa":{"a":0,"k":0,"ix":5},"nm":"Transform"}],"nm":"Group 1","np":28,"cix":2,"bm":0,"ix":1,"mn":"ADBE Vector Group","hd":false}],"ip":0,"op":120,"st":0,"ct":1,"bm":0}],"markers":[],"props":{}}